{
    "servicios": [
      {
        "nombre": "Soldadura MIG",
        "descripcion": "Soldadura de alta velocidad y eficiencia, ideal para trabajos en metales no ferrosos.",
        "precio": 100
      },
      {
        "nombre": "Soldadura TIG",
        "descripcion": "Ofrece gran precisión y control, ideal para metales delgados y trabajos detallados.",
        "precio": 200
      },
      {
        "nombre": "Soldadura por arco",
        "descripcion": "Método tradicional y versátil para una amplia gama de aplicaciones.",
        "precio": 300
      },
      {
        "nombre": "Soldadura de aluminio",
        "descripcion": "Especializada en trabajos con aluminio, garantizando uniones fuertes y duraderas.",
        "precio": 400
      }
    ]
  }